setup.cfg
setup.py
servicenow_rest/__init__.py
servicenow_rest/api.py
servicenow_rest.egg-info/PKG-INFO
servicenow_rest.egg-info/SOURCES.txt
servicenow_rest.egg-info/dependency_links.txt
servicenow_rest.egg-info/requires.txt
servicenow_rest.egg-info/top_level.txt