Metadata-Version: 1.1
Name: servicenow-rest
Version: 0.2.2
Summary: ServiceNow REST API Client
Home-page: https://github.com/rbw0/python-servicenow-rest
Author: Robert Wikman
Author-email: rbw@vault13.org
License: GPLv2
Download-URL: https://github.com/rbw0/python-servicenow-rest/tarball/0.2.2
Keywords: servicenow,rest,api
Platform: UNKNOWN
